pyhtk/HTKFeat.py
pyhtk-0.1.0.dist-info/METADATA
pyhtk-0.1.0.dist-info/WHEEL
pyhtk-0.1.0.dist-info/licenses/LICENSE
pyhtk-0.1.0.dist-info/RECORD
