Metadata-Version: 2.4
Name: pyhtk
Version: 0.1.0
Summary: This project contains a Python implementation of the MFCC features as computed by HTK.
License: Apache-2.0
License-File: LICENSE
Author: Danijel Korzinek
Author-email: danijel@korzinek.com
Requires-Python: >=3.9.0
Classifier: License :: OSI Approved :: Apache Software License
Classifier: Programming Language :: Python :: 3
Classifier: Programming Language :: Python :: 3.9
Classifier: Programming Language :: Python :: 3.10
Classifier: Programming Language :: Python :: 3.11
Classifier: Programming Language :: Python :: 3.12
Classifier: Programming Language :: Python :: 3.13
Classifier: Programming Language :: Python :: 3.14
Provides-Extra: tests
Requires-Dist: matplotlib (>=3.0.0) ; extra == "tests"
Requires-Dist: numpy (>=2.0.0)
